[
    {
        "_xt_meta": {
            "author": "佚名",
            "created_at": "2026-06-22 08:53:22",
            "note": "",
            "schema": 1,
            "tags": null,
            "title": "他"
        },
        "actual_combo": 0,
        "combo_stats": {
            "damage": 2140,
            "drive_used": 0,
            "super_used": 0
        },
        "counter_type": 0,
        "damage_at_step": 800,
        "delay_from_prev": 0,
        "dual_threshold": false,
        "expected_combo": 1,
        "expected_hp": 1,
        "facing_left": false,
        "group_id": 1,
        "has_hit": true,
        "hold_frames": 0,
        "hold_partial_check": false,
        "id": 631,
        "is_holdable": false,
        "is_projectile_hit": false,
        "motion": "2HP",
        "recorded_by": 0,
        "start_pos_p1": 0.2506988525390625,
        "start_pos_p1_raw": 1642980,
        "start_pos_p2": 1.5,
        "start_pos_p2_raw": 9830400,
        "timeline": [
            "5f : 2",
            "6f : 2+HP",
            "2f : 2",
            "2f : 3",
            "5f : 6",
            "1f : 5",
            "6f : 5+MP",
            "89f : 5"
        ]
    },
    {
        "actual_combo": 0,
        "counter_type": 0,
        "damage_at_step": 2140,
        "delay_from_prev": 25,
        "dual_threshold": false,
        "expected_combo": 2,
        "expected_hp": 1,
        "facing_left": false,
        "group_id": 2,
        "has_hit": true,
        "hold_frames": 0,
        "hold_partial_check": true,
        "id": 986,
        "is_holdable": false,
        "is_projectile_hit": true,
        "motion": "214+MP/HP"
    }
]